Workbook

Sheet start up cost 
A1: Start up cost/ Capital Expenditure
A2: Category | B2: Total Cost (GHS)
A3: Pullets (25,000 chicks) | B3: =B16*B17 -> 675000
A4: Housing Construction | B4: 890000
A5: Automated Watering System | B5: 160000
A6: Biosecurity & Fencing | B6: 27000
A7: Storage & Utility Blocks | B7: 70000
A8: Sanitation & PPE | B8: 35000
A9: Office/Admin Setup | B9: 25000
A10: Total Capital Needed | B10: =SUM(B3:B9) -> 1882000
G14: 1
A15: raw data
A16: pullets | B16: 27
A17: number of chicks | B17: 25000

Sheet operating expenses
A1: operating expenses
A2: Expense | B2: Monthly (GHS) | C2: Annual (GHS) | D2: percentage
A3: Feed | B3: =750000*0.4 -> 300000 | C3: =Table2[[#This Row],[Monthly (GHS)]]*12 -> 3600000 | D3: =Table2[[#This Row],[Monthly (GHS)]]/B10 -> 0.56963828
A4: Veterinary/Medication | B4: 67570 | C4: =Table2[[#This Row],[Monthly (GHS)]]*12 -> 810840 | D4: =Table2[[#This Row],[Monthly (GHS)]]/B10 -> 0.12830153
A5: Labor (15 @ GHS 1000) | B5: =15*1000 -> 15000 | C5: 432000 | D5: =Table2[[#This Row],[Monthly (GHS)]]/B10 -> 0.028481914
A6: Packaging (egg trays) | B6: 100080 | C6: 1200960 | D6: =Table2[[#This Row],[Monthly (GHS)]]/B10 -> 0.19003133
A7: Rent & Utilities | B7: 25000 | C7: 540000 | D7: =Table2[[#This Row],[Monthly (GHS)]]/B10 -> 0.047469857
A8: Admin & Operations | B8: 10000 | C8: 144000 | D8: =Table2[[#This Row],[Monthly (GHS)]]/B10 -> 0.018987943
A9: Repairs & Maintenance | B9: 9000 | C9: 288000 | D9: =Table2[[#This Row],[Monthly (GHS)]]/B10 -> 0.017089148
A10: Total Operating Cost | B10: =SUM(B3:B9) -> 526650 | C10: =SUM(C3:C9) -> 7015800

Sheet production outcome 
A1: Production Outcome
A2: Metric | B2: Value
A3: No. of Pullet | B3: 25000
A4: Egg Rate(Weekly) | B4: 5
A5: Weekly Output | B5: =B3*B4 -> 125000
A6: Monthly Output | B6: =4*B5 -> 500000
A7: Annual Output | B7: =12*B6 -> 6000000
A8: Crate (30 unit of eggs ) monthly | B8: =B6/30 -> 16666.667
A9: Crate (30 unit of eggs ) Annual | B9: =B7/30 -> 200000

Sheet revenue estimation
A1: Revenue Projection
A2: Items | B2: Value | C2: Total Revenue
A3: Number of Crate (Monthly ) | B3: ='production outcome '!B8 -> 16666.667 | C3: =B3*B5 -> 833333.33
A4: Number of Crate (Annual) | B4: ='production outcome '!B9 -> 200000 | C4: =B4*B5 -> 10000000
A5: Price per crate | B5: 50

Sheet Income Statement 
A1: Income statement
A2: Line Item | B2: Q1 | C2: Q2 | D2: Q3 | E2: Q4 | F2: Q5 | G2: Q6 | H2: Q7 | I2: Q8 | J2: Y2 Total | K2: Y1Total
A3: Revenue
A4: ‣ crate of Eggs | B4: 0 | C4: =0 -> 0 | D4: ='production outcome '!B8*3 -> 50000 | E4: =Table6[[#This Row],[Q3]] -> 50000 | F4: =Table6[[#This Row],[Q4]] -> 50000 | G4: =Table6[[#This Row],[Q5]] -> 50000 | H4: =Table6[[#This Row],[Q6]] -> 50000 | I4: =Table6[[#This Row],[Q7]] -> 50000 | J4: =SUM(Table6[[#This Row],[Q5]:[Q8]]) -> 200000 | K4: =SUM(Table6[[#This Row],[Q1]:[Q4]]) -> 100000
A5: Price Per Crate | B5: 0 | C5: =0 -> 0 | D5: =Table5[[#This Row],[Value ]] -> 50 | E5: =Table6[[#This Row],[Q3]] -> 50 | F5: =Table6[[#This Row],[Q4]] -> 50 | G5: =Table6[[#This Row],[Q5]] -> 50 | H5: =Table6[[#This Row],[Q6]] -> 50 | I5: =Table6[[#This Row],[Q7]] -> 50 | J5: =Table6[[#This Row],[Q8]] -> 50 | K5: =Table6[[#This Row],[Y2 Total]] -> 50
A6: Total Revenue | B6: =B5*B4 -> 0 | C6: =C5*C4 -> 0 | D6: =D5*D4 -> 2500000 | E6: =E5*E4 -> 2500000 | F6: =F5*F4 -> 2500000 | G6: =G5*G4 -> 2500000 | H6: =H5*H4 -> 2500000 | I6: =I5*I4 -> 2500000 | J6: =SUM(Table6[[#This Row],[Q5]:[Q8]]) -> 10000000 | K6: =K5*K4 -> 5000000
A7: Cost of Goods Sold (COGS)
A8: ‣ Feed | B8: ='operating expenses'!B3*3 -> 900000 | C8: =Table6[[#This Row],[Q1]] -> 900000 | D8: =Table6[[#This Row],[Q2]] -> 900000 | E8: =Table6[[#This Row],[Q3]] -> 900000 | F8: =Table6[[#This Row],[Q4]] -> 900000 | G8: =Table6[[#This Row],[Q2]] -> 900000 | H8: =Table6[[#This Row],[Q3]] -> 900000 | I8: =Table6[[#This Row],[Q4]] -> 900000 | J8: =SUM(Table6[[#This Row],[Q5]:[Q8]]) -> 3600000 | K8: =SUM(Table6[[#This Row],[Q1]:[Q4]]) -> 3600000
A9: ‣ Veterinary & Medication | B9: ='operating expenses'!B4*3 -> 202710 | C9: =Table6[[#This Row],[Q1]] -> 202710 | D9: =Table6[[#This Row],[Q2]] -> 202710 | E9: =Table6[[#This Row],[Q3]] -> 202710 | F9: =Table6[[#This Row],[Q4]] -> 202710 | G9: =Table6[[#This Row],[Q5]] -> 202710 | H9: =Table6[[#This Row],[Q6]] -> 202710 | I9: =Table6[[#This Row],[Q7]] -> 202710 | J9: =SUM(Table6[[#This Row],[Q5]:[Q8]]) -> 810840 | K9: =SUM(Table6[[#This Row],[Q1]:[Q4]]) -> 810840
A10: ‣ Packaging | B10: 0 | C10: 0 | D10: ='operating expenses'!B6*3 -> 300240 | E10: ='operating expenses'!B6*3 -> 300240 | F10: =Table6[[#This Row],[Q4]] -> 300240 | G10: =Table6[[#This Row],[Q5]] -> 300240 | H10: =Table6[[#This Row],[Q6]] -> 300240 | I10: =Table6[[#This Row],[Q7]] -> 300240 | J10: =SUM(Table6[[#This Row],[Q5]:[Q8]]) -> 1200960 | K10: =SUM(Table6[[#This Row],[Q1]:[Q4]]) -> 600480
A12: Total COGS | B12: =-SUM(B8:B10) -> -1102710 | C12: =-SUM(C8:C10) -> -1102710 | D12: =-SUM(D8:D10) -> -1402950 | E12: =-SUM(E8:E10) -> -1402950 | F12: =-SUM(F8:F10) -> -1402950 | G12: =-SUM(G8:G10) -> -1402950 | H12: =-SUM(H8:H10) -> -1402950 | I12: =-SUM(I8:I10) -> -1402950 | J12: =SUM(Table6[[#This Row],[Q5]:[Q8]]) -> -5611800 | K12: =-SUM(K8:K10) -> -5011320
A13: Gross Profit | B13: =SUM(B12,B6) -> -1102710 | C13: =SUM(C12,C6) -> -1102710 | D13: =SUM(D12,D6) -> 1097050 | E13: =SUM(E12,E6) -> 1097050 | F13: =SUM(F12,F6) -> 1097050 | G13: =SUM(G12,G6) -> 1097050 | H13: =SUM(H12,H6) -> 1097050 | I13: =SUM(I12,I6) -> 1097050 | J13: =SUM(Table6[[#This Row],[Q5]:[Q8]]) -> 4388200 | K13: =SUM(K12,K6) -> -11320
A14: Operating Expenses | J14: =SUM(Table6[[#This Row],[Q5]:[Q8]]) -> 0
A15: ‣ Utilities | B15: ='operating expenses'!B7*3 -> 75000 | C15: 75000 | D15: 75000 | E15: 75000 | F15: 75000 | G15: 75000 | H15: 75000 | I15: 75000 | J15: =SUM(Table6[[#This Row],[Q5]:[Q8]]) -> 300000 | K15: =SUM(Table6[[#This Row],[Q1]:[Q4]]) -> 300000
A16: ‣ Repairs & Maintenance | B16: ='operating expenses'!B9*3 -> 27000 | C16: =Table6[[#This Row],[Q1]] -> 27000 | D16: =Table6[[#This Row],[Q2]]*0.2 -> 5400 | E16: =Table6[[#This Row],[Q3]] -> 5400 | F16: =Table6[[#This Row],[Q4]] -> 5400 | G16: =Table6[[#This Row],[Q5]] -> 5400 | H16: =Table6[[#This Row],[Q6]] -> 5400 | I16: =Table6[[#This Row],[Q7]] -> 5400 | J16: =SUM(Table6[[#This Row],[Q5]:[Q8]]) -> 21600 | K16: =SUM(Table6[[#This Row],[Q1]:[Q4]]) -> 64800
A17: ‣ Admin & General Expenses | B17: ='operating expenses'!B8 *3 -> 30000 | C17: =Table6[[#This Row],[Q1]] -> 30000 | D17: =Table6[[#This Row],[Q2]] -> 30000 | E17: =Table6[[#This Row],[Q3]] -> 30000 | F17: 36000 | G17: 36000 | H17: 21000 | I17: 36000 | J17: =SUM(Table6[[#This Row],[Q5]:[Q8]]) -> 129000 | K17: =SUM(Table6[[#This Row],[Q1]:[Q4]]) -> 120000
A18: ‣ Labor | B18: ='operating expenses'!B5*3 -> 45000 | C18: ='operating expenses'!B5*3 -> 45000 | D18: =Table6[[#This Row],[Q2]] -> 45000 | E18: =Table6[[#This Row],[Q3]] -> 45000 | F18: =Table6[[#This Row],[Q4]] -> 45000 | G18: =Table6[[#This Row],[Q3]] -> 45000 | H18: =Table6[[#This Row],[Q4]] -> 45000 | I18: =Table6[[#This Row],[Q3]] -> 45000 | J18: =SUM(Table6[[#This Row],[Q5]:[Q8]]) -> 180000 | K18: =SUM(Table6[[#This Row],[Q1]:[Q4]]) -> 180000
A19: Total Operating Expenses | B19: =-SUM(B15:B18) -> -177000 | C19: =-SUM(C15:C18) -> -177000 | D19: =-SUM(D15:D18) -> -155400 | E19: =-SUM(E15:E18) -> -155400 | F19: =-SUM(F15:F18) -> -161400 | G19: =-SUM(G15:G18) -> -161400 | H19: =-SUM(H15:H18) -> -146400 | I19: =-SUM(I15:I18) -> -161400 | J19: =SUM(Table6[[#This Row],[Q5]:[Q8]]) -> -630600 | K19: =-SUM(K15:K18) -> -664800
A20: EBIT | B20: =SUM(B13,B19) -> -1279710 | C20: =SUM(C13,C19) -> -1279710 | D20: =SUM(D13,D19) -> 941650 | E20: =SUM(E13,E19) -> 941650 | F20: =SUM(F13,F19) -> 935650 | G20: =SUM(G13,G19) -> 935650 | H20: =SUM(H13,H19) -> 950650 | I20: =SUM(I13,I19) -> 935650 | J20: =SUM(Table6[[#This Row],[Q5]:[Q8]]) -> 3757600 | K20: =SUM(K13,K19) -> -676120
A21: Interest Expense | B21: 0 | C21: 0 | D21: 0 | E21: 0 | F21: 0 | G21: 0 | H21: 0 | I21: 0 | J21: =SUM(Table6[[#This Row],[Q5]:[Q8]]) -> 0 | K21: 0
A22: Tax Provision (0%) | B22: 0 | C22: 0 | D22: 0 | E22: 0 | F22: 0 | G22: 0 | H22: 0 | I22: 0 | J22: =SUM(Table6[[#This Row],[Q5]:[Q8]]) -> 0 | K22: 0
A23: Net Profit After Tax | B23: =SUM(B20:B22) -> -1279710 | C23: =SUM(C20:C22) -> -1279710 | D23: =SUM(D20:D22) -> 941650 | E23: =SUM(E20:E22) -> 941650 | F23: =SUM(F20:F22) -> 935650 | G23: =SUM(G20:G22) -> 935650 | H23: =SUM(H20:H22) -> 950650 | I23: =SUM(I20:I22) -> 935650 | J23: =SUM(Table6[[#This Row],[Q5]:[Q8]]) -> 3757600 | K23: =SUM(K20:K22) -> -676120
I27: Total profit at the end of the year 2 | J27: =J23+K23 -> 3081480
I28: Initial Cost | J28: ='start up cost '!B10 -> 1882000
I29: Net Profit | J29: =J27-'start up cost '!B10 -> 1199480
I30: ROI | J30: =J29/'start up cost '!B10 -> 0.63734325

Sheet Cash Flow Statement 
A1: Cash Flow Statement
A2: Cash Flow Item | B2: Q1 (GHS) | C2: Q2 (GHS) | D2: Q3 (GHS) | E2: Q4 (GHS) | F2: Q5 (GHS) | G2: Q6 (GHS) | H2: Q7 (GHS) | I2: Q8 (GHS) | J2: Year 2 Total (GHS) | K2: Annual Total (GHS)
A3: Egg Sales (GHS 50/crate) | B3: ='Income Statement '!B5 -> 0 | C3: 0 | D3: 2500000 | E3: 2500000 | F3: =Table10[[#This Row],[Q3 (GHS)]] -> 2500000 | G3: =Table10[[#This Row],[Q4 (GHS)]] -> 2500000 | H3: =Table10[[#This Row],[Q5 (GHS)]] -> 2500000 | I3: =Table10[[#This Row],[Q5 (GHS)]] -> 2500000 | J3: 10000000 | K3: 5000000
A4: Total Inflows | B4: ='Income Statement '!B6 -> 0 | C4: ='Income Statement '!C6 -> 0 | D4: ='Income Statement '!D6 -> 2500000 | E4: ='Income Statement '!E6 -> 2500000 | F4: ='Income Statement '!F6 -> 2500000 | G4: ='Income Statement '!G6 -> 2500000 | H4: ='Income Statement '!H6 -> 2500000 | I4: ='Income Statement '!I6 -> 2500000 | J4: =SUM(Table10[[#This Row],[Q5 (GHS)]:[Q8 (GHS)]]) -> 10000000 | K4: =SUM(Table10[[#This Row],[Q1 (GHS)]:[Q4 (GHS)]]) -> 5000000
A5: Feed | B5: ='Income Statement '!B8 -> 900000 | C5: ='Income Statement '!C8 -> 900000 | D5: ='Income Statement '!D8 -> 900000 | E5: ='Income Statement '!E8 -> 900000 | F5: =Table10[[#This Row],[Q1 (GHS)]] -> 900000 | G5: =Table10[[#This Row],[Q2 (GHS)]] -> 900000 | H5: =Table10[[#This Row],[Q3 (GHS)]] -> 900000 | I5: =Table10[[#This Row],[Q4 (GHS)]] -> 900000 | J5: =SUM(Table10[[#This Row],[Q5 (GHS)]:[Q8 (GHS)]]) -> 3600000 | K5: 4003200
A6: Veterinary & Medication | B6: ='Income Statement '!B9 -> 202710 | C6: ='Income Statement '!C9 -> 202710 | D6: ='Income Statement '!D9 -> 202710 | E6: ='Income Statement '!E9 -> 202710 | F6: =Table10[[#This Row],[Q1 (GHS)]] -> 202710 | G6: =Table10[[#This Row],[Q2 (GHS)]] -> 202710 | H6: =Table10[[#This Row],[Q3 (GHS)]] -> 202710 | I6: =Table10[[#This Row],[Q4 (GHS)]] -> 202710 | J6: =SUM(Table10[[#This Row],[Q5 (GHS)]:[Q8 (GHS)]]) -> 810840 | K6: 810840
A7: Packaging | B7: ='Income Statement '!B10 -> 0 | C7: ='Income Statement '!C10 -> 0 | D7: ='Income Statement '!D10 -> 300240 | E7: ='Income Statement '!E10 -> 300240 | F7: =Table10[[#This Row],[Q3 (GHS)]] -> 300240 | G7: =Table10[[#This Row],[Q4 (GHS)]] -> 300240 | H7: =Table10[[#This Row],[Q4 (GHS)]] -> 300240 | I7: =Table10[[#This Row],[Q4 (GHS)]] -> 300240 | J7: 1200960 | K7: 600480
A8: Utilities | B8: ='Income Statement '!B15 -> 75000 | C8: 75000 | D8: 75000 | E8: 75000 | F8: =Table10[[#This Row],[Q1 (GHS)]] -> 75000 | G8: =Table10[[#This Row],[Q2 (GHS)]] -> 75000 | H8: =Table10[[#This Row],[Q3 (GHS)]] -> 75000 | I8: =Table10[[#This Row],[Q4 (GHS)]] -> 75000 | J8: =SUM(Table10[[#This Row],[Q5 (GHS)]:[Q8 (GHS)]]) -> 300000 | K8: 300000
A9: Repairs & Maintenance | B9: ='Income Statement '!B16 -> 27000 | C9: ='Income Statement '!C16 -> 27000 | D9: ='Income Statement '!D16 -> 5400 | E9: ='Income Statement '!E16 -> 5400 | F9: =Table10[[#This Row],[Q1 (GHS)]] -> 27000 | G9: =Table10[[#This Row],[Q2 (GHS)]] -> 27000 | H9: =Table10[[#This Row],[Q3 (GHS)]] -> 5400 | I9: =Table10[[#This Row],[Q4 (GHS)]] -> 5400 | J9: =SUM(Table10[[#This Row],[Q5 (GHS)]:[Q8 (GHS)]]) -> 64800 | K9: 108000
A10: Admin & General Expenses | B10: ='Income Statement '!B17 -> 30000 | C10: ='Income Statement '!C17 -> 30000 | D10: ='Income Statement '!D17 -> 30000 | E10: ='Income Statement '!E17 -> 30000 | F10: =Table10[[#This Row],[Q1 (GHS)]] -> 30000 | G10: =Table10[[#This Row],[Q2 (GHS)]] -> 30000 | H10: =Table10[[#This Row],[Q3 (GHS)]] -> 30000 | I10: =Table10[[#This Row],[Q4 (GHS)]] -> 30000 | J10: =SUM(Table10[[#This Row],[Q5 (GHS)]:[Q8 (GHS)]]) -> 120000 | K10: 134500
A11: Labor | B11: ='Income Statement '!B18 -> 45000 | C11: ='Income Statement '!C18 -> 45000 | D11: ='Income Statement '!D18 -> 45000 | E11: ='Income Statement '!E18 -> 45000 | F11: =SUM(Table10[[#This Row],[Q1 (GHS)]]) -> 45000 | G11: =SUM(Table10[[#This Row],[Q2 (GHS)]]) -> 45000 | H11: =SUM(Table10[[#This Row],[Q3 (GHS)]]) -> 45000 | I11: =SUM(Table10[[#This Row],[Q4 (GHS)]]) -> 45000 | J11: =SUM(Table10[[#This Row],[Q5 (GHS)]:[Q8 (GHS)]]) -> 180000 | K11: 180000
A12: Total Outflows | B12: =-SUM(B5:B11) -> -1279710 | C12: =-SUM(C5:C11) -> -1279710 | D12: =-SUM(D5:D11) -> -1558350 | E12: =-SUM(E5:E11) -> -1558350 | F12: =-SUM(F5:F11) -> -1579950 | G12: =-SUM(G5:G11) -> -1579950 | H12: =-SUM(H5:H11) -> -1558350 | I12: =-SUM(I5:I11) -> -1558350 | J12: =-SUM(J5:J11) -> -6276600 | K12: =SUM(Table10[[#This Row],[Q1 (GHS)]:[Q4 (GHS)]]) -> -5676120
A13: Net Cash Flow | B13: =SUM(B4,B12) -> -1279710 | C13: =SUM(C4,C12) -> -1279710 | D13: =SUM(D4,D12) -> 941650 | E13: =SUM(E4,E12) -> 941650 | F13: =SUM(F4,F12) -> 920050 | G13: =SUM(G4,G12) -> 920050 | H13: =SUM(H4,H12) -> 941650 | I13: =SUM(I4,I12) -> 941650 | J13: =SUM(Table10[[#This Row],[Q5 (GHS)]:[Q8 (GHS)]]) -> 3723400 | K13: =SUM(Table10[[#This Row],[Q1 (GHS)]:[Q4 (GHS)]]) -> -676120
A14: Cumulative Cash Flow | B14: =SUM(B13) -> -1279710 | C14: =SUM(Table10[[#This Row],[Q1 (GHS)]],C13) -> -2559420 | D14: =SUM(Table10[[#This Row],[Q2 (GHS)]],D13) -> -1617770 | E14: =SUM(Table10[[#This Row],[Q3 (GHS)]],E13) -> -676120 | F14: =SUM(Table10[[#This Row],[Q4 (GHS)]],F13) -> 243930 | G14: =SUM(Table10[[#This Row],[Q5 (GHS)]],G13) -> 1163980 | H14: =SUM(Table10[[#This Row],[Q6 (GHS)]],H13) -> 2105630 | I14: =SUM(Table10[[#This Row],[Q7 (GHS)]],I13) -> 3047280
C16: Discount Rate | D16: 0.12
C17: NPV | D17: =NPV(D16,J13,K13)-'Income Statement '!J28 -> 903465.56
